LICENSE.txt
MANIFEST.in
README.md
setup.cfg
setup.py
config/constant_ast.json
config/decl_ast.json
config/funccall_ast.json
config/funcdef_ast.json
config/id_ast.json
secularize/__init__.py
secularize/char.py
secularize/parser.py
secularize/token.py
secularize/utils.py
secularize.egg-info/PKG-INFO
secularize.egg-info/SOURCES.txt
secularize.egg-info/dependency_links.txt
secularize.egg-info/entry_points.txt
secularize.egg-info/requires.txt
secularize.egg-info/top_level.txt
secularize/__pycache__/__init__.cpython-37.pyc
secularize/__pycache__/char.cpython-37.pyc
secularize/__pycache__/parser.cpython-37.pyc
secularize/__pycache__/token.cpython-37.pyc
secularize/__pycache__/utils.cpython-37.pyc