Metadata-Version: 1.1
Name: secularize
Version: 0.0.1.post6
Summary: run HolyC source on linux
Home-page: https://www.github.com/jamesalbert/HolyC-for-Linux
Author: jamesalbert
Author-email: jamesrobertalbert@gmail.com
License: MIT
Keywords: holyc linux terry lord temple mlg
Platform: UNKNOWN
Classifier: Development Status :: 3 - Alpha
Classifier: Intended Audience :: Developers
Classifier: Topic :: Software Development :: Build Tools
Classifier: License :: OSI Approved :: MIT License
Classifier: Programming Language :: Python :: 3.6
